ComradeAI/DocumentRoutines.py
ComradeAI/Mycelium.py
ComradeAI/Processors.py
ComradeAI/__init__.py
ComradeAI-0.18.28.dist-info/LICENSE
ComradeAI-0.18.28.dist-info/METADATA
ComradeAI-0.18.28.dist-info/WHEEL
ComradeAI-0.18.28.dist-info/top_level.txt
ComradeAI-0.18.28.dist-info/RECORD
