Metadata-Version: 2.1
Name: ComradeAI
Version: 0.18.28
Summary: A protocol and SDK for unified AI service interaction
Home-page: https://github.com/SergeiKarulin/ComradeAI
Author: Sergei Karulin
Author-email: sk@spellsystems.com
Classifier: Programming Language :: Python :: 3
Classifier: License :: OSI Approved :: MIT License
Classifier: Operating System :: OS Independent
License-File: LICENSE
Requires-Dist: aiohttp
Requires-Dist: aio-pika
Requires-Dist: beautifulsoup4
Requires-Dist: openpyxl
Requires-Dist: pika
Requires-Dist: Pillow
Requires-Dist: requests
